wardhere_py/__init__.py
wardhere_py/greet_module.py
Wardhere-0.1.0.dist-info/LICENSE
Wardhere-0.1.0.dist-info/METADATA
Wardhere-0.1.0.dist-info/WHEEL
Wardhere-0.1.0.dist-info/top_level.txt
Wardhere-0.1.0.dist-info/RECORD
