Metadata-Version: 2.1
Name: Wardhere
Version: 0.1.0
Summary: A simple Python package to greet people. Note: I created this package for testing package creation in Python.
Home-page: https://packaging.python.org/en/latest/tutorials/packaging-projects/
Author: Badrudin Mohamed Ali
Author-email: badrudin.dev@gmail.com
Classifier: Programming Language :: Python :: 3
Classifier: License :: OSI Approved :: MIT License
Classifier: Operating System :: OS Independent
License-File: LICENSE
